cytotrace2_py/__init__.py
cytotrace2_py/cytotrace2_py.py
cytotrace2_py/common/argument_parser.py
cytotrace2_py/common/gen_utils.py
cytotrace2_py/common/models.py
cytotrace2_py/common/plot.py
cytotrace2_py/resources/background.pt
cytotrace2_py/resources/features_model_training.csv
cytotrace2_py/resources/human_alias_list.txt
cytotrace2_py/resources/mart_export.txt
cytotrace2_py/resources/mouse_alias_list.txt
cytotrace2_py-1.1.0.3.dist-info/METADATA
cytotrace2_py-1.1.0.3.dist-info/WHEEL
cytotrace2_py-1.1.0.3.dist-info/entry_points.txt
cytotrace2_py-1.1.0.3.dist-info/top_level.txt
cytotrace2_py-1.1.0.3.dist-info/RECORD
