Metadata-Version: 2.4
Name: cytotrace2_py
Version: 1.1.0.3
Summary: CytoTRACE 2 is a computational method for predicting cellular potency categories and absolute developmental potential from single-cell RNA-sequencing data.
Author-email: "CytoTRACE 2 Team, Newman Lab" <cytotrace2team@gmail.com>
Project-URL: Homepage, https://github.com/digitalcytometry/cytotrace2/tree/main/cytotrace2_python
Project-URL: Issues, https://github.com/digitalcytometry/cytotrace2/issues
Project-URL: License, https://github.com/digitalcytometry/cytotrace2/blob/main/LICENSE
Classifier: Programming Language :: Python :: 3
Classifier: License :: Other/Proprietary License
Classifier: Operating System :: OS Independent
Requires-Python: >=3.9
Requires-Dist: anndata
Requires-Dist: numpy<2.0.0
Requires-Dist: pandas
Requires-Dist: scanpy
Requires-Dist: scipy
Requires-Dist: scikit-learn>=1.0.2
Requires-Dist: torch>=2.0.0
Requires-Dist: gdown
Provides-Extra: docs
Requires-Dist: sphinx>=4.0; extra == "docs"
Requires-Dist: sphinx-rtd-theme>=0.5.0; extra == "docs"
Provides-Extra: tests
Requires-Dist: pytest>=6.2.4; extra == "tests"
Requires-Dist: pytest-cov>=2.12.1; extra == "tests"
